NightWind3DLib3/Actor.py
NightWind3DLib3/CreateFog.py
NightWind3DLib3/FieldForest.egg.pz
NightWind3DLib3/Friend.py
NightWind3DLib3/GroundNeedle.egg
NightWind3DLib3/GroundNeedle_motion.egg
NightWind3DLib3/GroundNeedle_stop.egg
NightWind3DLib3/Needle.py
NightWind3DLib3/Player.py
NightWind3DLib3/Rescue.py
NightWind3DLib3/Woodmen.py
NightWind3DLib3/__init__.py
NightWind3DLib3/aduan.egg
NightWind3DLib3/aduan_life.png
NightWind3DLib3/aduan_stand.egg
NightWind3DLib3/aduan_walk.egg
NightWind3DLib3/codemao.egg
NightWind3DLib3/codemao_life.png
NightWind3DLib3/codemao_stand.egg
NightWind3DLib3/codemao_walk.egg
NightWind3DLib3/font.ttc
NightWind3DLib3/introduction.png
NightWind3DLib3/laser.egg
NightWind3DLib3/lose.png
NightWind3DLib3/start.png
NightWind3DLib3/win.png
NightWind3DLib3/woodmen.egg
NightWind3DLib3/woodmen_attack.egg
NightWind3DLib3/woodmen_die.egg
NightWind3DLib3/woodmen_life.png
NightWind3DLib3/woodmen_stand.egg
NightWind3DLib3/woodmen_walk.egg
NightWind3DLib3/__pycache__/Actor.cpython-39.pyc
NightWind3DLib3/__pycache__/CreateFog.cpython-39.pyc
NightWind3DLib3/__pycache__/Friend.cpython-39.pyc
NightWind3DLib3/__pycache__/Needle.cpython-39.pyc
NightWind3DLib3/__pycache__/Player.cpython-39.pyc
NightWind3DLib3/__pycache__/Woodmen.cpython-39.pyc
NightWind3DLib3/__pycache__/__init__.cpython-39.pyc
NightWind3DLib3/texture/PY_AD.png
NightWind3DLib3/texture/Special_1.png
NightWind3DLib3/texture/Xunizhubo-codemao.jpg
NightWind3DLib3/texture/dichi.png
NightWind3DLib3/texture/dimian.png
NightWind3DLib3/texture/hemispherical_003_Paint.png
NightWind3DLib3/texture/jyxiangrikui_02_a01_a.tga
NightWind3DLib3/texture/laser.png
NightWind3DLib3/texture/mutouren.png
NightWind3DLib3/texture/shanlan.png
NightWind3DLib3/texture/shitou.png
NightWind3DLib3/texture/shugan.png
NightWind3DLib3/texture/shugan.tga
NightWind3DLib3/texture/shuye.tga
NightWind3DLib3/texture/shuye2.tga
NightWind3DLib3-1.0.0.dist-info/METADATA
NightWind3DLib3-1.0.0.dist-info/WHEEL
NightWind3DLib3-1.0.0.dist-info/top_level.txt
NightWind3DLib3-1.0.0.dist-info/RECORD
